sample_env/__init__.py
sample_env/__main__.py
sample_env/py.typed
sample_env-1.0.0.dist-info/licenses/LICENSE
sample_env-1.0.0.dist-info/METADATA
sample_env-1.0.0.dist-info/WHEEL
sample_env-1.0.0.dist-info/entry_points.txt
sample_env-1.0.0.dist-info/top_level.txt
sample_env-1.0.0.dist-info/RECORD
