Metadata-Version: 2.4
Name: sample-env
Version: 1.0.0
Summary: A command line tool for generating sample env files from pydantic BaseSettings.
Author-email: sandbox <sandbox@sandbox.com.np>
Project-URL: Homepage, https://github.com/sandbox-pokhara/sample-env
Project-URL: Issues, https://github.com/sandbox-pokhara/sample-env/issues
Classifier: Programming Language :: Python :: 3
Requires-Python: >=3.10
License-File: LICENSE
Requires-Dist: pydantic
Requires-Dist: pydantic-settings
Requires-Dist: pydantic-core
Provides-Extra: pre-commit
Requires-Dist: pre-commit; extra == "pre-commit"
Provides-Extra: build
Requires-Dist: build; extra == "build"
Requires-Dist: wheel; extra == "build"
Requires-Dist: setuptools; extra == "build"
Dynamic: license-file
